browser_driver/__init__.py
browser_driver/browser.py
sjb.browserdriver-0.1.3.dist-info/METADATA
sjb.browserdriver-0.1.3.dist-info/RECORD
sjb.browserdriver-0.1.3.dist-info/WHEEL
sjb.browserdriver-0.1.3.dist-info/top_level.txt
tests/__init__.py
tests/browser_tests.py
