Metadata-Version: 2.1
Name: sjb.browserdriver
Version: 0.1.3
Summary: Browser Driver is a Wrapper for Selenium Web Automation
Home-page: https://github.com/shawnjburke/browser_driver
Author: 'Shawn J Burke'
Author-email: pypi.python@teamburke.com
License: MIT
Project-URL: Bug Tracker, https://github.com/shawnjburke/browser_driver/issues/
Project-URL: Documentation, https://shawnjburke.github.io/browser_driver/
Project-URL: Source Code, https://github.com/shawnjburke/browser_driver/
Keywords: selenium test testing automation browser
Platform: UNKNOWN
Classifier: Development Status :: 4 - Beta
Classifier: Intended Audience :: Developers
Classifier: License :: OSI Approved :: MIT License
Classifier: Natural Language :: English
Classifier: Operating System :: OS Independent
Classifier: Programming Language :: Python
Classifier: Programming Language :: Python :: 2.7
Classifier: Programming Language :: Python :: 3
Classifier: Programming Language :: Python :: 3.3
Classifier: Programming Language :: Python :: 3.4
Classifier: Programming Language :: Python :: 3.5
Classifier: Programming Language :: Python :: 3.6
Classifier: Programming Language :: Python :: Implementation :: CPython
Classifier: Topic :: Software Development :: Quality Assurance
Classifier: Topic :: Software Development :: Testing
Requires-Dist: configparser2 (==4.0.0)
Requires-Dist: selenium (==3.12.0)
